healthriskanalysis/__init__.py
healthriskanalysis/statics.py
healthriskanalysis-0.1.0.dist-info/licenses/LICENCE
healthriskanalysis-0.1.0.dist-info/METADATA
healthriskanalysis-0.1.0.dist-info/WHEEL
healthriskanalysis-0.1.0.dist-info/top_level.txt
healthriskanalysis-0.1.0.dist-info/RECORD
