Metadata-Version: 2.4
Name: healthriskanalysis
Version: 0.1.0
Summary: Health risk analysis tool
Author-email: Senin Adın <senin@email.com>
Requires-Python: >=3.8
License-File: LICENCE
Dynamic: license-file
